
{"items":[{"name":"JobOfferData","href":"JobOfferData.html","topicHref":"JobOfferData.html","topicUid":"JobOfferData","type":"Namespace","items":[{"name":"MockData","href":"JobOfferData.MockData.html","topicHref":"JobOfferData.MockData.html","topicUid":"JobOfferData.MockData","type":"Class"}]},{"name":"JobOfferDataClasses","href":"JobOfferDataClasses.html","topicHref":"JobOfferDataClasses.html","topicUid":"JobOfferDataClasses","type":"Namespace","items":[{"name":"Department","href":"JobOfferDataClasses.Department.html","topicHref":"JobOfferDataClasses.Department.html","topicUid":"JobOfferDataClasses.Department","type":"Class"},{"name":"ExecutiveUserProfile","href":"JobOfferDataClasses.ExecutiveUserProfile.html","topicHref":"JobOfferDataClasses.ExecutiveUserProfile.html","topicUid":"JobOfferDataClasses.ExecutiveUserProfile","type":"Class"},{"name":"FirstPage","href":"JobOfferDataClasses.FirstPage.html","topicHref":"JobOfferDataClasses.FirstPage.html","topicUid":"JobOfferDataClasses.FirstPage","type":"Class"},{"name":"Hreflang","href":"JobOfferDataClasses.Hreflang.html","topicHref":"JobOfferDataClasses.Hreflang.html","topicUid":"JobOfferDataClasses.Hreflang","type":"Class"},{"name":"JobDescriptionItem","href":"JobOfferDataClasses.JobDescriptionItem.html","topicHref":"JobOfferDataClasses.JobDescriptionItem.html","topicUid":"JobOfferDataClasses.JobDescriptionItem","type":"Class"},{"name":"JobDescriptionPage","href":"JobOfferDataClasses.JobDescriptionPage.html","topicHref":"JobOfferDataClasses.JobDescriptionPage.html","topicUid":"JobOfferDataClasses.JobDescriptionPage","type":"Class"},{"name":"JobPosition","href":"JobOfferDataClasses.JobPosition.html","topicHref":"JobOfferDataClasses.JobPosition.html","topicUid":"JobOfferDataClasses.JobPosition","type":"Class"},{"name":"Meta","href":"JobOfferDataClasses.Meta.html","topicHref":"JobOfferDataClasses.Meta.html","topicUid":"JobOfferDataClasses.Meta","type":"Class"},{"name":"MetaContainer","href":"JobOfferDataClasses.MetaContainer.html","topicHref":"JobOfferDataClasses.MetaContainer.html","topicUid":"JobOfferDataClasses.MetaContainer","type":"Class"},{"name":"Paging","href":"JobOfferDataClasses.Paging.html","topicHref":"JobOfferDataClasses.Paging.html","topicUid":"JobOfferDataClasses.Paging","type":"Class"},{"name":"PlaceOfEmployment","href":"JobOfferDataClasses.PlaceOfEmployment.html","topicHref":"JobOfferDataClasses.PlaceOfEmployment.html","topicUid":"JobOfferDataClasses.PlaceOfEmployment","type":"Class"},{"name":"User","href":"JobOfferDataClasses.User.html","topicHref":"JobOfferDataClasses.User.html","topicUid":"JobOfferDataClasses.User","type":"Class"}]},{"name":"JobOfferTests","href":"JobOfferTests.html","topicHref":"JobOfferTests.html","topicUid":"JobOfferTests","type":"Namespace","items":[{"name":"JobOfferTests","href":"JobOfferTests.JobOfferTests.html","topicHref":"JobOfferTests.JobOfferTests.html","topicUid":"JobOfferTests.JobOfferTests","type":"Class"}]}],"memberLayout":"SamePage","pdf":true}
